LICENSE
README.md
setup.py
src/imobject/__init__.py
src/imobject/exception.py
src/imobject/improved_list.py
src/imobject/ioc.py
src/imobject/obj_dict.py
src/imobject/orm_collection.py
src/imobject.egg-info/PKG-INFO
src/imobject.egg-info/SOURCES.txt
src/imobject.egg-info/dependency_links.txt
src/imobject.egg-info/top_level.txt