Metadata-Version: 2.1
Name: imobject
Version: 2.0.1
Summary: Imporve object
Home-page: https://github.com/mzakariabigdata/imobject
Author: Zakaria Morchid
Author-email: morchid.zakariaa@gmail.com
Project-URL: Bug Tracker, https://github.com/mzakariabigdata/imobject/issues
Classifier: Programming Language :: Python :: 3
Classifier: License :: OSI Approved :: MIT License
Classifier: Operating System :: OS Independent
Requires-Python: >=3.7
License-File: LICENSE
